setup.py
ccsnmultivar/GWUtils.py
ccsnmultivar/__init__.py
ccsnmultivar/basis.py
ccsnmultivar/catalog.py
ccsnmultivar/designmatrix.py
ccsnmultivar/multivar.py
ccsnmultivar.egg-info/PKG-INFO
ccsnmultivar.egg-info/SOURCES.txt
ccsnmultivar.egg-info/dependency_links.txt
ccsnmultivar.egg-info/requires.txt
ccsnmultivar.egg-info/top_level.txt