Metadata-Version: 1.1
Name: ccsnmultivar
Version: 0.0.5
Summary: Multivariate regression analysis of core-collapse simulations
Home-page: https://github.com/bwengals/CCSNMultivar
Author: Bill Engels
Author-email: w.j.engels@gmail.com
License: UNKNOWN
Download-URL: https://github.com/bwengals/CCSNMultivar/tarball/0.1
Keywords: multivariate,regression,core-collapse,supernova
Platform: any
